pydaybit/__init__.py
pydaybit/daybit.py
pydaybit/daybit_channels.py
pydaybit/exceptions.py
pydaybit/ratelimit.py
pydaybit/utility.py
pydaybit/phoenix/__init__.py
pydaybit/phoenix/channel.py
pydaybit/phoenix/exceptions.py
pydaybit/phoenix/message.py
pydaybit/phoenix/phoenix.py
pydaybit/subscriptions/__init__.py
pydaybit/subscriptions/subscription.py
pydaybit-0.0.3.4.dist-info/DESCRIPTION.rst
pydaybit-0.0.3.4.dist-info/METADATA
pydaybit-0.0.3.4.dist-info/RECORD
pydaybit-0.0.3.4.dist-info/WHEEL
pydaybit-0.0.3.4.dist-info/metadata.json
pydaybit-0.0.3.4.dist-info/top_level.txt
